generand/__init__.py
generand/bernoulli.py
generand/binomial.py
generand/erlang.py
generand/exponential.py
generand/geometric.py
generand/normal.py
generand/poisson.py
generand/triangular.py
generand/uniform.py
generand/weibull.py
generand-3.0.2.dist-info/METADATA
generand-3.0.2.dist-info/WHEEL
generand-3.0.2.dist-info/licenses/LICENSE
generand-3.0.2.dist-info/RECORD
