Metadata-Version: 2.1
Name: generand
Version: 3.0.2
Summary: A package to generate random numbers from various distributions
Project-URL: Homepage, https://github.com/pypa/generand
Project-URL: Bug Tracker, https://github.com/pypa/generand/issues
Author-email: rajat maheshwari <rajat.maheshwari30@gmail.com>, shanthan kesharaju <shanthan.kesharaju@gmail.com>
License-File: LICENSE
Classifier: License :: OSI Approved :: MIT License
Classifier: Operating System :: OS Independent
Classifier: Programming Language :: Python :: 3
Requires-Python: >=3.7
